printfuk/__init__.py
printfuk/printfuk.py
printfuk-0.0.3.dist-info/METADATA
printfuk-0.0.3.dist-info/WHEEL
printfuk-0.0.3.dist-info/top_level.txt
printfuk-0.0.3.dist-info/RECORD
