Metadata-Version: 2.1
Name: printfuk
Version: 0.0.3
Summary: Completely override your python print function with complete garbage that sometimes looks approximately correct
Home-page: https://github.com/HoldenMilne/printfuk
Author: Holden Milne
Author-email: holden.milne@gmail.com
License: UNKNOWN
Project-URL: Bug Tracker, https://github.com/printfuk/issues
Platform: UNKNOWN
Classifier: Programming Language :: Python :: 3
Classifier: License :: OSI Approved :: MIT License
Classifier: Operating System :: OS Independent
Requires-Python: >=3.6
